pybgpkitstream/__init__.py
pybgpkitstream/bgpelement.py
pybgpkitstream/bgpkitstream.py
pybgpkitstream/bgpparser.py
pybgpkitstream/bgpstreamconfig.py
pybgpkitstream/cli.py
pybgpkitstream/py.typed
pybgpkitstream/utils.py
pybgpkitstream-0.3.0.dist-info/WHEEL
pybgpkitstream-0.3.0.dist-info/entry_points.txt
pybgpkitstream-0.3.0.dist-info/METADATA
pybgpkitstream-0.3.0.dist-info/RECORD
