Metadata-Version: 2.3
Name: pybgpkitstream
Version: 0.3.0
Summary: Drop-in replacement for PyBGPStream using BGPKIT
Author: JustinLoye
Author-email: JustinLoye <jloye@iij.ad.jp>
Requires-Dist: aiohttp>=3.12.15
Requires-Dist: pybgpkit>=0.6.2
Requires-Dist: pydantic>=2.11.9
Requires-Python: >=3.10
